{"data":[{"Products":[{"listData":{"productId":"7a0122b1-3f9c-4872-87c9-50e886aeff3b","effectiveFrom":"2022-06-29T03:54:40.033Z","effectiveTo":"9999-12-30T13:00:00Z","lastUpdated":"2023-10-19T03:43:43.000Z","productCategory":"RESIDENTIAL_MORTGAGES","name":"Low doc home loan","description":"Low doc home loans","brand":"Liberty Financial","brandName":"Liberty Financial","isTailored":false,"additionalInformation":{}},"detailData":{"bundles":[],"features":[],"constraints":[],"eligibility":[],"fees":[],"depositRates":[],"productId":"7a0122b1-3f9c-4872-87c9-50e886aeff3b","effectiveFrom":"2022-06-29T03:54:40.033Z","effectiveTo":"9999-12-30T13:00:00Z","lastUpdated":"2023-10-19T03:43:43.000Z","productCategory":"RESIDENTIAL_MORTGAGES","name":"Low doc home loan","description":"Low doc home loans","brand":"Liberty Financial","brandName":"Liberty Financial","isTailored":false,"additionalInformation":{}},"ID":"7a0122b1-3f9c-4872-87c9-50e886aeff3b"},{"listData":{"productId":"830aa2c3-49a7-4472-b1a7-87a10e7605c7","effectiveFrom":"2022-06-09T02:13:29.031Z","effectiveTo":"9999-12-30T13:00:00Z","lastUpdated":"2023-10-19T00:22:29.000Z","productCategory":"PERS_LOANS","name":"Low doc car loan","description":"Low doc car loans","brand":"Liberty Financial","brandName":"Liberty Financial","isTailored":false,"additionalInformation":{}},"detailData":{"bundles":[],"features":[],"constraints":[],"eligibility":[],"fees":[],"depositRates":[],"productId":"830aa2c3-49a7-4472-b1a7-87a10e7605c7","effectiveFrom":"2022-06-09T02:13:29.031Z","effectiveTo":"9999-12-30T13:00:00Z","lastUpdated":"2023-10-19T00:22:29.000Z","productCategory":"PERS_LOANS","name":"Low doc car loan","description":"Low doc car loans","brand":"Liberty Financial","brandName":"Liberty Financial","isTailored":false,"additionalInformation":{}},"ID":"830aa2c3-49a7-4472-b1a7-87a10e7605c7"},{"listData":{"productId":"4ab135c2-2407-40cf-b272-3ade65698076","effectiveFrom":"2022-06-09T02:21:01.663Z","effectiveTo":"9999-12-30T13:00:00Z","lastUpdated":"2023-10-10T05:37:12.000Z","productCategory":"PERS_LOANS","name":"Flexible car loan","description":"Flexible car loans","brand":"Liberty Financial","brandName":"Liberty Financial","isTailored":false,"additionalInformation":{}},"detailData":{"bundles":[],"features":[],"constraints":[],"eligibility":[],"fees":[],"depositRates":[],"productId":"4ab135c2-2407-40cf-b272-3ade65698076","effectiveFrom":"2022-06-09T02:21:01.663Z","effectiveTo":"9999-12-30T13:00:00Z","lastUpdated":"2023-10-10T05:37:12.000Z","productCategory":"PERS_LOANS","name":"Flexible car loan","description":"Flexible car loans","brand":"Liberty Financial","brandName":"Liberty Financial","isTailored":false,"additionalInformation":{}},"ID":"4ab135c2-2407-40cf-b272-3ade65698076"},{"listData":{"productId":"fb1985b5-29aa-428a-9b75-a90734364ff4","effectiveFrom":"2022-06-09T01:55:18.463Z","effectiveTo":"9999-12-30T13:00:00Z","lastUpdated":"2023-10-10T05:37:12.000Z","productCategory":"PERS_LOANS","name":"Fresh start car loan","description":"Fresh start car loans","brand":"Liberty Financial","brandName":"Liberty Financial","isTailored":false,"additionalInformation":{}},"detailData":{"bundles":[],"features":[],"constraints":[],"eligibility":[],"fees":[],"depositRates":[],"productId":"fb1985b5-29aa-428a-9b75-a90734364ff4","effectiveFrom":"2022-06-09T01:55:18.463Z","effectiveTo":"9999-12-30T13:00:00Z","lastUpdated":"2023-10-10T05:37:12.000Z","productCategory":"PERS_LOANS","name":"Fresh start car loan","description":"Fresh start car loans","brand":"Liberty Financial","brandName":"Liberty Financial","isTailored":false,"additionalInformation":{}},"ID":"fb1985b5-29aa-428a-9b75-a90734364ff4"},{"listData":{"productId":"00dbdc4e-0b48-4982-a02e-545b334b1d5c","effectiveFrom":"2022-06-07T05:43:26.017Z","effectiveTo":"9999-12-30T13:00:00Z","lastUpdated":"2023-10-05T02:25:51.000Z","productCategory":"BUSINESS_LOANS","name":"Residential SMSF loan","description":"Residential SMSF loans","brand":"Liberty Financial","brandName":"Liberty Financial","isTailored":false,"additionalInformation":{}},"detailData":{"bundles":[],"features":[],"constraints":[],"eligibility":[],"fees":[],"depositRates":[],"productId":"00dbdc4e-0b48-4982-a02e-545b334b1d5c","effectiveFrom":"2022-06-07T05:43:26.017Z","effectiveTo":"9999-12-30T13:00:00Z","lastUpdated":"2023-10-05T02:25:51.000Z","productCategory":"BUSINESS_LOANS","name":"Residential SMSF loan","description":"Residential SMSF loans","brand":"Liberty Financial","brandName":"Liberty Financial","isTailored":false,"additionalInformation":{}},"ID":"00dbdc4e-0b48-4982-a02e-545b334b1d5c"},{"listData":{"productId":"ea0a982d-f0ad-40c9-9d92-9b8234ae839c","effectiveFrom":"2022-06-14T07:41:41.243Z","effectiveTo":"9999-12-30T13:00:00Z","lastUpdated":"2023-10-05T02:25:51.000Z","productCategory":"RESIDENTIAL_MORTGAGES","name":"Low deposit investment loan","description":"Low deposit investment loans","brand":"Liberty Financial","brandName":"Liberty Financial","isTailored":false,"additionalInformation":{}},"detailData":{"bundles":[],"features":[],"constraints":[],"eligibility":[],"fees":[],"depositRates":[],"productId":"ea0a982d-f0ad-40c9-9d92-9b8234ae839c","effectiveFrom":"2022-06-14T07:41:41.243Z","effectiveTo":"9999-12-30T13:00:00Z","lastUpdated":"2023-10-05T02:25:51.000Z","productCategory":"RESIDENTIAL_MORTGAGES","name":"Low deposit investment loan","description":"Low deposit investment loans","brand":"Liberty Financial","brandName":"Liberty Financial","isTailored":false,"additionalInformation":{}},"ID":"ea0a982d-f0ad-40c9-9d92-9b8234ae839c"},{"listData":{"productId":"8ab1738a-9d31-49db-ab95-7d8716fe31c1","effectiveFrom":"2022-06-15T01:32:55.995Z","effectiveTo":"9999-12-30T13:00:00Z","lastUpdated":"2023-10-05T02:25:51.000Z","productCategory":"RESIDENTIAL_MORTGAGES","name":"Fresh start home loan","description":"Fresh start home loans","brand":"Liberty Financial","brandName":"Liberty Financial","isTailored":false,"additionalInformation":{}},"detailData":{"bundles":[],"features":[],"constraints":[],"eligibility":[],"fees":[],"depositRates":[],"productId":"8ab1738a-9d31-49db-ab95-7d8716fe31c1","effectiveFrom":"2022-06-15T01:32:55.995Z","effectiveTo":"9999-12-30T13:00:00Z","lastUpdated":"2023-10-05T02:25:51.000Z","productCategory":"RESIDENTIAL_MORTGAGES","name":"Fresh start home loan","description":"Fresh start home loans","brand":"Liberty Financial","brandName":"Liberty Financial","isTailored":false,"additionalInformation":{}},"ID":"8ab1738a-9d31-49db-ab95-7d8716fe31c1"},{"listData":{"productId":"71352589-e22c-46cc-a754-cff4f2377575","effectiveFrom":"2022-06-29T03:42:02.491Z","effectiveTo":"9999-12-30T13:00:00Z","lastUpdated":"2023-10-05T02:25:51.000Z","productCategory":"RESIDENTIAL_MORTGAGES","name":"Low doc investment loan","description":"Low doc investment loans","brand":"Liberty Financial","brandName":"Liberty Financial","isTailored":false,"additionalInformation":{}},"detailData":{"bundles":[],"features":[],"constraints":[],"eligibility":[],"fees":[],"depositRates":[],"productId":"71352589-e22c-46cc-a754-cff4f2377575","effectiveFrom":"2022-06-29T03:42:02.491Z","effectiveTo":"9999-12-30T13:00:00Z","lastUpdated":"2023-10-05T02:25:51.000Z","productCategory":"RESIDENTIAL_MORTGAGES","name":"Low doc investment loan","description":"Low doc investment loans","brand":"Liberty Financial","brandName":"Liberty Financial","isTailored":false,"additionalInformation":{}},"ID":"71352589-e22c-46cc-a754-cff4f2377575"},{"listData":{"productId":"ce2338e1-b797-40f2-8e7f-80488ae41f94","effectiveFrom":"2022-06-09T01:30:44.768Z","effectiveTo":"9999-12-30T13:00:00Z","lastUpdated":"2023-10-05T02:25:51.000Z","productCategory":"PERS_LOANS","name":"Unsecured personal loan","description":"Unsecured personal loans","brand":"Liberty Financial","brandName":"Liberty Financial","isTailored":false,"additionalInformation":{}},"detailData":{"bundles":[],"features":[],"constraints":[],"eligibility":[],"fees":[],"depositRates":[],"productId":"ce2338e1-b797-40f2-8e7f-80488ae41f94","effectiveFrom":"2022-06-09T01:30:44.768Z","effectiveTo":"9999-12-30T13:00:00Z","lastUpdated":"2023-10-05T02:25:51.000Z","productCategory":"PERS_LOANS","name":"Unsecured personal loan","description":"Unsecured personal loans","brand":"Liberty Financial","brandName":"Liberty Financial","isTailored":false,"additionalInformation":{}},"ID":"ce2338e1-b797-40f2-8e7f-80488ae41f94"},{"listData":{"productId":"eb16c08a-4670-4a24-adf0-2f72e8d57f1f","effectiveFrom":"2022-06-14T02:32:16.781Z","effectiveTo":"9999-12-30T13:00:00Z","lastUpdated":"2023-10-05T02:25:51.000Z","productCategory":"RESIDENTIAL_MORTGAGES","name":"Flexible home loan","description":"Flexible home loans","brand":"Liberty Financial","brandName":"Liberty Financial","isTailored":false,"additionalInformation":{}},"detailData":{"bundles":[],"features":[],"constraints":[],"eligibility":[],"fees":[],"depositRates":[],"productId":"eb16c08a-4670-4a24-adf0-2f72e8d57f1f","effectiveFrom":"2022-06-14T02:32:16.781Z","effectiveTo":"9999-12-30T13:00:00Z","lastUpdated":"2023-10-05T02:25:51.000Z","productCategory":"RESIDENTIAL_MORTGAGES","name":"Flexible home loan","description":"Flexible home loans","brand":"Liberty Financial","brandName":"Liberty Financial","isTailored":false,"additionalInformation":{}},"ID":"eb16c08a-4670-4a24-adf0-2f72e8d57f1f"},{"listData":{"productId":"90be67ce-9427-4f58-84a2-2c73cccfaa58","effectiveFrom":"2022-06-09T00:56:10.094Z","effectiveTo":"9999-12-30T13:00:00Z","lastUpdated":"2023-10-05T02:25:51.000Z","productCategory":"PERS_LOANS","name":"Secured personal loan","description":"Secured personal loans","brand":"Liberty Financial","brandName":"Liberty Financial","isTailored":false,"additionalInformation":{}},"detailData":{"bundles":[],"features":[],"constraints":[],"eligibility":[],"fees":[],"depositRates":[],"productId":"90be67ce-9427-4f58-84a2-2c73cccfaa58","effectiveFrom":"2022-06-09T00:56:10.094Z","effectiveTo":"9999-12-30T13:00:00Z","lastUpdated":"2023-10-05T02:25:51.000Z","productCategory":"PERS_LOANS","name":"Secured personal loan","description":"Secured personal loans","brand":"Liberty Financial","brandName":"Liberty Financial","isTailored":false,"additionalInformation":{}},"ID":"90be67ce-9427-4f58-84a2-2c73cccfaa58"},{"listData":{"productId":"690e034e-a1c5-4aea-ba09-830b86a129b6","effectiveFrom":"2022-06-15T01:19:44.970Z","effectiveTo":"9999-12-30T13:00:00Z","lastUpdated":"2023-10-05T02:25:51.000Z","productCategory":"RESIDENTIAL_MORTGAGES","name":"Debt consolidation home loan","description":"Debt consolidation home loans","brand":"Liberty Financial","brandName":"Liberty Financial","isTailored":false,"additionalInformation":{}},"detailData":{"bundles":[],"features":[],"constraints":[],"eligibility":[],"fees":[],"depositRates":[],"productId":"690e034e-a1c5-4aea-ba09-830b86a129b6","effectiveFrom":"2022-06-15T01:19:44.970Z","effectiveTo":"9999-12-30T13:00:00Z","lastUpdated":"2023-10-05T02:25:51.000Z","productCategory":"RESIDENTIAL_MORTGAGES","name":"Debt consolidation home loan","description":"Debt consolidation home loans","brand":"Liberty Financial","brandName":"Liberty Financial","isTailored":false,"additionalInformation":{}},"ID":"690e034e-a1c5-4aea-ba09-830b86a129b6"},{"listData":{"productId":"712fd94c-946a-4ceb-8ef0-c76def48afb4","effectiveFrom":"2022-06-29T23:16:48.807Z","effectiveTo":"9999-12-30T13:00:00Z","lastUpdated":"2023-10-05T02:25:51.000Z","productCategory":"RESIDENTIAL_MORTGAGES","name":"Flexible investment loan","description":"Flexible investment loans","brand":"Liberty Financial","brandName":"Liberty Financial","isTailored":false,"additionalInformation":{}},"detailData":{"bundles":[],"features":[],"constraints":[],"eligibility":[],"fees":[],"depositRates":[],"productId":"712fd94c-946a-4ceb-8ef0-c76def48afb4","effectiveFrom":"2022-06-29T23:16:48.807Z","effectiveTo":"9999-12-30T13:00:00Z","lastUpdated":"2023-10-05T02:25:51.000Z","productCategory":"RESIDENTIAL_MORTGAGES","name":"Flexible investment loan","description":"Flexible investment loans","brand":"Liberty Financial","brandName":"Liberty Financial","isTailored":false,"additionalInformation":{}},"ID":"712fd94c-946a-4ceb-8ef0-c76def48afb4"},{"listData":{"productId":"05501e53-ad4f-4396-9a0a-0fa3c6b8daee","effectiveFrom":"2022-06-15T01:40:12.781Z","effectiveTo":"9999-12-30T13:00:00Z","lastUpdated":"2023-10-05T02:25:51.000Z","productCategory":"RESIDENTIAL_MORTGAGES","name":"Fresh start investment loan","description":"Fresh start investment loans","brand":"Liberty Financial","brandName":"Liberty Financial","isTailored":false,"additionalInformation":{}},"detailData":{"bundles":[],"features":[],"constraints":[],"eligibility":[],"fees":[],"depositRates":[],"productId":"05501e53-ad4f-4396-9a0a-0fa3c6b8daee","effectiveFrom":"2022-06-15T01:40:12.781Z","effectiveTo":"9999-12-30T13:00:00Z","lastUpdated":"2023-10-05T02:25:51.000Z","productCategory":"RESIDENTIAL_MORTGAGES","name":"Fresh start investment loan","description":"Fresh start investment loans","brand":"Liberty Financial","brandName":"Liberty Financial","isTailored":false,"additionalInformation":{}},"ID":"05501e53-ad4f-4396-9a0a-0fa3c6b8daee"},{"listData":{"productId":"d42e3fdd-ff27-47ca-812b-2dc54aad75af","effectiveFrom":"2022-06-14T02:44:23.416Z","effectiveTo":"9999-12-30T13:00:00Z","lastUpdated":"2023-10-05T02:25:51.000Z","productCategory":"RESIDENTIAL_MORTGAGES","name":"Low rate investment loan","description":"Low rate investment loans","brand":"Liberty Financial","brandName":"Liberty Financial","isTailored":false,"additionalInformation":{}},"detailData":{"bundles":[],"features":[],"constraints":[],"eligibility":[],"fees":[],"depositRates":[],"productId":"d42e3fdd-ff27-47ca-812b-2dc54aad75af","effectiveFrom":"2022-06-14T02:44:23.416Z","effectiveTo":"9999-12-30T13:00:00Z","lastUpdated":"2023-10-05T02:25:51.000Z","productCategory":"RESIDENTIAL_MORTGAGES","name":"Low rate investment loan","description":"Low rate investment loans","brand":"Liberty Financial","brandName":"Liberty Financial","isTailored":false,"additionalInformation":{}},"ID":"d42e3fdd-ff27-47ca-812b-2dc54aad75af"},{"listData":{"productId":"b9200a53-74fd-4d37-91af-753fa446355f","effectiveFrom":"2022-03-17T04:26:30.950Z","effectiveTo":"9999-12-30T13:00:00Z","lastUpdated":"2023-10-05T02:25:51.000Z","productCategory":"RESIDENTIAL_MORTGAGES","name":"Low rate home loan","description":"Low rate home loans","brand":"Liberty Financial","brandName":"Liberty Financial","isTailored":false,"additionalInformation":{}},"detailData":{"bundles":[],"features":[],"constraints":[],"eligibility":[],"fees":[],"depositRates":[],"productId":"b9200a53-74fd-4d37-91af-753fa446355f","effectiveFrom":"2022-03-17T04:26:30.950Z","effectiveTo":"9999-12-30T13:00:00Z","lastUpdated":"2023-10-05T02:25:51.000Z","productCategory":"RESIDENTIAL_MORTGAGES","name":"Low rate home loan","description":"Low rate home loans","brand":"Liberty Financial","brandName":"Liberty Financial","isTailored":false,"additionalInformation":{}},"ID":"b9200a53-74fd-4d37-91af-753fa446355f"},{"listData":{"productId":"581a8d2c-9190-415e-afb2-0dec1c24caf8","effectiveFrom":"2022-06-09T22:39:26.202Z","effectiveTo":"9999-12-30T13:00:00Z","lastUpdated":"2023-09-22T00:42:47.000Z","productCategory":"BUSINESS_LOANS","name":"Secured business loan","description":"Secured business loans","brand":"Liberty Financial","brandName":"Liberty Financial","isTailored":false,"additionalInformation":{}},"detailData":{"bundles":[],"features":[],"constraints":[],"eligibility":[],"fees":[],"depositRates":[],"productId":"581a8d2c-9190-415e-afb2-0dec1c24caf8","effectiveFrom":"2022-06-09T22:39:26.202Z","effectiveTo":"9999-12-30T13:00:00Z","lastUpdated":"2023-09-22T00:42:47.000Z","productCategory":"BUSINESS_LOANS","name":"Secured business loan","description":"Secured business loans","brand":"Liberty Financial","brandName":"Liberty Financial","isTailored":false,"additionalInformation":{}},"ID":"581a8d2c-9190-415e-afb2-0dec1c24caf8"},{"listData":{"productId":"b0a3d1a9-0db9-4e37-abc4-8b3b8f0e4ca3","effectiveFrom":"2022-06-10T07:17:32.214Z","effectiveTo":"9999-12-30T13:00:00Z","lastUpdated":"2023-09-22T00:42:47.000Z","productCategory":"BUSINESS_LOANS","name":"Low rate commercial loan","description":"Low rate commercial loans","brand":"Liberty Financial","brandName":"Liberty Financial","isTailored":false,"additionalInformation":{}},"detailData":{"bundles":[],"features":[],"constraints":[],"eligibility":[],"fees":[],"depositRates":[],"productId":"b0a3d1a9-0db9-4e37-abc4-8b3b8f0e4ca3","effectiveFrom":"2022-06-10T07:17:32.214Z","effectiveTo":"9999-12-30T13:00:00Z","lastUpdated":"2023-09-22T00:42:47.000Z","productCategory":"BUSINESS_LOANS","name":"Low rate commercial loan","description":"Low rate commercial loans","brand":"Liberty Financial","brandName":"Liberty Financial","isTailored":false,"additionalInformation":{}},"ID":"b0a3d1a9-0db9-4e37-abc4-8b3b8f0e4ca3"},{"listData":{"productId":"7805a6c8-2f6d-4a93-8479-5fdaab52af78","effectiveFrom":"2022-06-10T05:32:19.810Z","effectiveTo":"9999-12-30T13:00:00Z","lastUpdated":"2023-09-22T00:42:47.000Z","productCategory":"BUSINESS_LOANS","name":"Lease income loan","description":"Lease income loans","brand":"Liberty Financial","brandName":"Liberty Financial","isTailored":false,"additionalInformation":{}},"detailData":{"bundles":[],"features":[],"constraints":[],"eligibility":[],"fees":[],"depositRates":[],"productId":"7805a6c8-2f6d-4a93-8479-5fdaab52af78","effectiveFrom":"2022-06-10T05:32:19.810Z","effectiveTo":"9999-12-30T13:00:00Z","lastUpdated":"2023-09-22T00:42:47.000Z","productCategory":"BUSINESS_LOANS","name":"Lease income loan","description":"Lease income loans","brand":"Liberty Financial","brandName":"Liberty Financial","isTailored":false,"additionalInformation":{}},"ID":"7805a6c8-2f6d-4a93-8479-5fdaab52af78"},{"listData":{"productId":"ff73e566-161a-4c85-a179-7fddd3f1d1b5","effectiveFrom":"2022-06-10T02:52:27.291Z","effectiveTo":"9999-12-30T13:00:00Z","lastUpdated":"2023-09-22T00:42:47.000Z","productCategory":"BUSINESS_LOANS","name":"Business line of credit","description":"Business line of credits","brand":"Liberty Financial","brandName":"Liberty Financial","isTailored":false,"additionalInformation":{}},"detailData":{"bundles":[],"features":[],"constraints":[],"eligibility":[],"fees":[],"depositRates":[],"productId":"ff73e566-161a-4c85-a179-7fddd3f1d1b5","effectiveFrom":"2022-06-10T02:52:27.291Z","effectiveTo":"9999-12-30T13:00:00Z","lastUpdated":"2023-09-22T00:42:47.000Z","productCategory":"BUSINESS_LOANS","name":"Business line of credit","description":"Business line of credits","brand":"Liberty Financial","brandName":"Liberty Financial","isTailored":false,"additionalInformation":{}},"ID":"ff73e566-161a-4c85-a179-7fddd3f1d1b5"},{"listData":{"productId":"5a550c19-aa68-486f-843e-acb9ed6ebad9","effectiveFrom":"2022-06-10T07:10:14.361Z","effectiveTo":"9999-12-30T13:00:00Z","lastUpdated":"2023-09-22T00:42:47.000Z","productCategory":"BUSINESS_LOANS","name":"Short term commercial loan","description":"Short term commercial loans","brand":"Liberty Financial","brandName":"Liberty Financial","isTailored":false,"additionalInformation":{}},"detailData":{"bundles":[],"features":[],"constraints":[],"eligibility":[],"fees":[],"depositRates":[],"productId":"5a550c19-aa68-486f-843e-acb9ed6ebad9","effectiveFrom":"2022-06-10T07:10:14.361Z","effectiveTo":"9999-12-30T13:00:00Z","lastUpdated":"2023-09-22T00:42:47.000Z","productCategory":"BUSINESS_LOANS","name":"Short term commercial loan","description":"Short term commercial loans","brand":"Liberty Financial","brandName":"Liberty Financial","isTailored":false,"additionalInformation":{}},"ID":"5a550c19-aa68-486f-843e-acb9ed6ebad9"},{"listData":{"productId":"521fc98e-c5a3-4f6d-adc8-bbc1b663e42d","effectiveFrom":"2022-06-07T05:15:27.841Z","effectiveTo":"9999-12-30T13:00:00Z","lastUpdated":"2023-09-22T00:42:47.000Z","productCategory":"BUSINESS_LOANS","name":"Commercial SMSF loan","description":" Commercial SMSF loans","brand":"Liberty Financial","brandName":"Liberty Financial","isTailored":false,"additionalInformation":{}},"detailData":{"bundles":[],"features":[],"constraints":[],"eligibility":[],"fees":[],"depositRates":[],"productId":"521fc98e-c5a3-4f6d-adc8-bbc1b663e42d","effectiveFrom":"2022-06-07T05:15:27.841Z","effectiveTo":"9999-12-30T13:00:00Z","lastUpdated":"2023-09-22T00:42:47.000Z","productCategory":"BUSINESS_LOANS","name":"Commercial SMSF loan","description":" Commercial SMSF loans","brand":"Liberty Financial","brandName":"Liberty Financial","isTailored":false,"additionalInformation":{}},"ID":"521fc98e-c5a3-4f6d-adc8-bbc1b663e42d"},{"listData":{"productId":"5259b11b-d90d-41a9-a964-471cc8b02b1b","effectiveFrom":"2022-06-10T06:25:43.099Z","effectiveTo":"9999-12-30T13:00:00Z","lastUpdated":"2023-09-22T00:42:47.000Z","productCategory":"BUSINESS_LOANS","name":"Low doc commercial loan","description":"Low doc commercial loans","brand":"Liberty Financial","brandName":"Liberty Financial","isTailored":false,"additionalInformation":{}},"detailData":{"bundles":[],"features":[],"constraints":[],"eligibility":[],"fees":[],"depositRates":[],"productId":"5259b11b-d90d-41a9-a964-471cc8b02b1b","effectiveFrom":"2022-06-10T06:25:43.099Z","effectiveTo":"9999-12-30T13:00:00Z","lastUpdated":"2023-09-22T00:42:47.000Z","productCategory":"BUSINESS_LOANS","name":"Low doc commercial loan","description":"Low doc commercial loans","brand":"Liberty Financial","brandName":"Liberty Financial","isTailored":false,"additionalInformation":{}},"ID":"5259b11b-d90d-41a9-a964-471cc8b02b1b"},{"listData":{"productId":"5838dfc3-b759-4a6b-9da3-95efcb3b426f","effectiveFrom":"2023-06-15T00:54:04.005Z","effectiveTo":"9999-12-30T13:00:00Z","lastUpdated":"2023-09-22T00:42:47.000Z","productCategory":"BUSINESS_LOANS","name":"Low doc business loan","description":"Low doc business loans","brand":"Liberty Financial","brandName":"Liberty Financial","isTailored":false,"additionalInformation":{}},"detailData":{"bundles":[],"features":[],"constraints":[],"eligibility":[],"fees":[],"depositRates":[],"productId":"5838dfc3-b759-4a6b-9da3-95efcb3b426f","effectiveFrom":"2023-06-15T00:54:04.005Z","effectiveTo":"9999-12-30T13:00:00Z","lastUpdated":"2023-09-22T00:42:47.000Z","productCategory":"BUSINESS_LOANS","name":"Low doc business loan","description":"Low doc business loans","brand":"Liberty Financial","brandName":"Liberty Financial","isTailored":false,"additionalInformation":{}},"ID":"5838dfc3-b759-4a6b-9da3-95efcb3b426f"},{"listData":{"productId":"d9bc6f89-5367-4524-9e4c-6c6eefdd317d","effectiveFrom":"2022-06-10T02:41:21.924Z","effectiveTo":"9999-12-30T13:00:00Z","lastUpdated":"2023-09-22T00:42:47.000Z","productCategory":"BUSINESS_LOANS","name":"Flexible business loan","description":"Flexible business loans","brand":"Liberty Financial","brandName":"Liberty Financial","isTailored":false,"additionalInformation":{}},"detailData":{"bundles":[],"features":[],"constraints":[],"eligibility":[],"fees":[],"depositRates":[],"productId":"d9bc6f89-5367-4524-9e4c-6c6eefdd317d","effectiveFrom":"2022-06-10T02:41:21.924Z","effectiveTo":"9999-12-30T13:00:00Z","lastUpdated":"2023-09-22T00:42:47.000Z","productCategory":"BUSINESS_LOANS","name":"Flexible business loan","description":"Flexible business loans","brand":"Liberty Financial","brandName":"Liberty Financial","isTailored":false,"additionalInformation":{}},"ID":"d9bc6f89-5367-4524-9e4c-6c6eefdd317d"}],"Name":"Liberty Financial","NameDisplay":"Liberty Financial","LogoURL":"https://d2ttwt9gu7swv4.cloudfront.net/cdr_assets/Liberty-Aero-Horizontal-RGB.jpg","LastRefreshed":"2025-03-04T17:49:38.7248429+11:00"}]}